{
  "aor": 0.0016415962441314554,
  "aqi": 0.005601420892018779,
  "bids_meta": {
    "dataset": "ds001246",
    "modality": "bold",
    "run_id": 1,
    "session_id": "imageryTest02",
    "subject_id": "02",
    "task_id": "imagery"
  },
  "dummy_trs": 0,
  "dvars_nstd": 25.41317596084907,
  "dvars_std": 1.1753665161320754,
  "dvars_vstd": 1.022895390235849,
  "efc": 0.5629200737481215,
  "fber": 528.9086303710938,
  "fd_mean": 0.06357227664257982,
  "fd_num": 5,
  "fd_perc": 2.347417840375587,
  "fwhm_avg": 1.9100755555555555,
  "fwhm_x": 1.82502,
  "fwhm_y": 1.9748666666666665,
  "fwhm_z": 1.93034,
  "gcor": 0.0511178,
  "gsr_x": 0.016673514619469643,
  "gsr_y": 0.027315778657794,
  "provenance": {
    "md5sum": "d400561d5855c7d6fd48de7f86f332fa",
    "settings": {
      "fd_thres": 0.2,
      "testing": false
    },
    "software": "mriqc",
    "version": "23.1.0"
  },
  "size_t": 213,
  "size_x": 64,
  "size_y": 64,
  "size_z": 50,
  "snr": 4.075042294754362,
  "spacing_tr": 3.0,
  "spacing_x": 3.0,
  "spacing_y": 3.0,
  "spacing_z": 3.0,
  "summary_bg_k": 26.843778382555577,
  "summary_bg_mad": 17.380553657623107,
  "summary_bg_mean": 75.44948620286613,
  "summary_bg_median": 37.81690216064453,
  "summary_bg_n": 155393.0,
  "summary_bg_p05": 24.760562896728516,
  "summary_bg_p95": 285.93426513671875,
  "summary_bg_stdv": 99.73082661284124,
  "summary_fg_k": 1.7162451107410392,
  "summary_fg_mad": 168.82173560137073,
  "summary_fg_mean": 885.8431509825056,
  "summary_fg_median": 869.713623046875,
  "summary_fg_n": 49407.0,
  "summary_fg_p05": 550.7464599609375,
  "summary_fg_p95": 1268.01416015625,
  "summary_fg_stdv": 213.42228094162112,
  "tsnr": 65.06981086311862
}